[
  {
    "ContainingType": "EmployeeManagementAPI.Controllers.EmployeeController",
    "Method": "GetEmployee",
    "RelativePath": "api/Employee",
    "HttpMethod": "GET",
    "IsController": true,
    "Order": 0,
    "Parameters": [],
    "ReturnTypes": []
  },
  {
    "ContainingType": "EmployeeManagementAPI.Controllers.EmployeeController",
    "Method": "AddEmployee",
    "RelativePath": "api/Employee",
    "HttpMethod": "POST",
    "IsController": true,
    "Order": 0,
    "Parameters": [
      {
        "Name": "Employee",
        "Type": "EmployeeManagementAPI.DTO.CreateEmployeeDTO",
        "IsRequired": true
      }
    ],
    "ReturnTypes": []
  },
  {
    "ContainingType": "EmployeeManagementAPI.Controllers.EmployeeController",
    "Method": "GetByIdEmployee",
    "RelativePath": "api/Employee/{id}",
    "HttpMethod": "GET",
    "IsController": true,
    "Order": 0,
    "Parameters": [
      {
        "Name": "id",
        "Type": "System.Int32",
        "IsRequired": true
      }
    ],
    "ReturnTypes": []
  },
  {
    "ContainingType": "EmployeeManagementAPI.Controllers.EmployeeController",
    "Method": "UpdateEmployee",
    "RelativePath": "api/Employee/{id}",
    "HttpMethod": "PUT",
    "IsController": true,
    "Order": 0,
    "Parameters": [
      {
        "Name": "id",
        "Type": "System.Int32",
        "IsRequired": true
      },
      {
        "Name": "Employee",
        "Type": "EmployeeManagementAPI.DTO.UpdateEmployeeDTO",
        "IsRequired": true
      }
    ],
    "ReturnTypes": []
  },
  {
    "ContainingType": "EmployeeManagementAPI.Controllers.EmployeeController",
    "Method": "DeleteEmployee",
    "RelativePath": "api/Employee/{id}",
    "HttpMethod": "DELETE",
    "IsController": true,
    "Order": 0,
    "Parameters": [
      {
        "Name": "id",
        "Type": "System.Int32",
        "IsRequired": true
      }
    ],
    "ReturnTypes": []
  },
  {
    "ContainingType": "EmployeeManagementAPI.Controllers.WeatherForecastController",
    "Method": "Get",
    "RelativePath": "WeatherForecast",
    "HttpMethod": "GET",
    "IsController": true,
    "Order": 0,
    "Parameters": [],
    "ReturnTypes": [
      {
        "Type": "System.Collections.Generic.IEnumerable\u00601[[EmployeeManagementAPI.WeatherForecast, EmployeeManagementAPI, Version=1.0.0.0, Culture=neutral, PublicKeyToken=null]]",
        "MediaTypes": [
          "text/plain",
          "application/json",
          "text/json"
        ],
        "StatusCode": 200
      }
    ],
    "EndpointName": "GetWeatherForecast"
  }
]